jupyter_highlight_selected_word/__init__.py
jupyter_highlight_selected_word/static/highlight_selected_word/README.md
jupyter_highlight_selected_word/static/highlight_selected_word/configurator.yaml
jupyter_highlight_selected_word/static/highlight_selected_word/main.css
jupyter_highlight_selected_word/static/highlight_selected_word/main.js
jupyter_highlight_selected_word/static/highlight_selected_word/package.json
jupyter_highlight_selected_word-0.1.0.dist-info/DESCRIPTION.rst
jupyter_highlight_selected_word-0.1.0.dist-info/METADATA
jupyter_highlight_selected_word-0.1.0.dist-info/RECORD
jupyter_highlight_selected_word-0.1.0.dist-info/WHEEL
jupyter_highlight_selected_word-0.1.0.dist-info/metadata.json
jupyter_highlight_selected_word-0.1.0.dist-info/top_level.txt
