Metadata-Version: 1.0
Name: jupyter_highlight_selected_word
Version: 0.1.0
Summary: Jupyter notebook extension that enables highlighting every instance of the current word in the notebook.
Home-page: https://github.com/jcb91/jupyter_highlight_selected_word.git
Author: Joshua Cooke Barnes
Author-email: joshuacookebarnes@gmail.com
License: BSD
Platform: UNKNOWN
